LICENSE.txt
README.md
setup.py
ch_airflow_tools/__init__.py
ch_airflow_tools/logging.py
ch_airflow_tools/metrics.py
ch_airflow_tools/monitoring.py
ch_airflow_tools.egg-info/PKG-INFO
ch_airflow_tools.egg-info/SOURCES.txt
ch_airflow_tools.egg-info/dependency_links.txt
ch_airflow_tools.egg-info/not-zip-safe
ch_airflow_tools.egg-info/requires.txt
ch_airflow_tools.egg-info/top_level.txt