Metadata-Version: 2.1
Name: ch-airflow-tools
Version: 4.1
Summary: Apache Airflow tools
Author: Alex Yung
License-File: LICENSE.txt
